MANIFEST.in
README.rst
setup.cfg
setup.py
rvcm/__init__.py
rvcm/__main__.py
rvcm/calls.py
rvcm/cli.py
rvcm/nat.py
rvcm/router.py
rvcm.egg-info/PKG-INFO
rvcm.egg-info/SOURCES.txt
rvcm.egg-info/dependency_links.txt
rvcm.egg-info/entry_points.txt
rvcm.egg-info/requires.txt
rvcm.egg-info/top_level.txt