Metadata-Version: 1.1
Name: rvcm
Version: 1.0.7
Summary: Control RV6688BCM router
Home-page: https://github.com/reddec/router-control
Author: Baryshnikov Alexander
Author-email: dev@baryshnikov.net
License: MIT
Keywords: RV6688BCM router-control gpon rvcm
Platform: UNKNOWN
Classifier: Development Status :: 5 - Production/Stable
Classifier: Intended Audience :: System Administrators
Classifier: Topic :: System :: Systems Administration
Classifier: License :: OSI Approved :: MIT License
Classifier: Programming Language :: Python :: 3.5
